MANIFEST.in
README.rst
ez_setup.py
setup.py
django_weeny.egg-info/PKG-INFO
django_weeny.egg-info/SOURCES.txt
django_weeny.egg-info/dependency_links.txt
django_weeny.egg-info/requires.txt
django_weeny.egg-info/top_level.txt
weeny/__init__.py
weeny/admin.py
weeny/models.py
weeny/signals.py
weeny/urls.py
weeny/views.py
weeny/forms/__init__.py
weeny/forms/admin.py
weeny/forms/auth.py
weeny/migrations/0001_initial.py
weeny/migrations/0002_auto__add_field_weenyurl_is_removed__add_field_weenysite_redirect_shor.py
weeny/migrations/__init__.py
weeny/static/weeny/css/weeny.css
weeny/static/weeny/img/icon_alert.gif
weeny/static/weeny/img/nav-bg-reverse.gif
weeny/static/weeny/img/nav-bg.gif
weeny/templates/weeny/authenticate.html
weeny/tests/__init__.py