Metadata-Version: 1.1
Name: django-weeny
Version: 1.0.4
Summary: Small and simple URL shortener app for Django.
Home-page: https://bitbucket.org/mootacom/django-weeny
Author: Rolf Håvard Blindheim
Author-email: rhblind@gmail.com
License: Apache Software License
Download-URL: https://rhblind@bitbucket.org/mootacom/django-weeny.git
Platform: UNKNOWN
Classifier: Operating System :: OS Independent
Classifier: Development Status :: 4 - Beta
Classifier: Environment :: Web Environment
Classifier: Framework :: Django
Classifier: Intended Audience :: Developers
Classifier: License :: OSI Approved :: Apache Software License
Classifier: Programming Language :: Python :: 2
Classifier: Programming Language :: Python :: 2.7
Classifier: Programming Language :: Python :: 3
Classifier: Programming Language :: Python :: 3.4
Classifier: Topic :: Software Development :: Libraries :: Python Modules
